jsonrpc/client/__init__.py
jsonrpc/client/base.py
jsonrpc/client/exceptions.py
jsonrpc/client/transport/__init__.py
jsonrpc/client/transport/base.py
jsonrpc/client/transport/http.py
jsonrpc/client/transport/websocket.py
jsonrpc_asyncio_client-0.1.0.dist-info/METADATA
jsonrpc_asyncio_client-0.1.0.dist-info/WHEEL
jsonrpc_asyncio_client-0.1.0.dist-info/top_level.txt
jsonrpc_asyncio_client-0.1.0.dist-info/RECORD
